LICENSE
README
README.md
dotgitconfig.py
dotnetrc.py
jira2data.py
jira2data_api.py
odoo2data.py
odoo2data_api.py
odootopic.py
setup.cfg
setup.py
tabtools.py
tabtotext.py
tabtoxlsx.py
timerange.py
timetrack.py
zeit2jira.py
zeit2json.py
zeit2odoo.py
timetrack_odoo.egg-info/PKG-INFO
timetrack_odoo.egg-info/SOURCES.txt
timetrack_odoo.egg-info/dependency_links.txt
timetrack_odoo.egg-info/requires.txt
timetrack_odoo.egg-info/top_level.txt