Metadata-Version: 2.1
Name: timetrack-odoo
Version: 1.0.2102
Summary: Synchronize odoo-import data with Odoo Timesheet and Jira Worklogs
Home-page: https://github.com/gdraheim/timetrack-odoo
Author: Guido U. Draheim
Author-email: Guido.Draheim@gmx.de
License: APL
Platform: UNKNOWN
